{
  "Version": "2012-10-17",
  "Statement": [
    {
      "Sid": "VPC",
      "Effect": "Allow",
      "Action": [
        "ec2:CreateVpc",
        "ec2:DeleteVpc",
        "ec2:ModifyVpcAttribute",
        "ec2:DescribeVpcs",
        "ec2:DescribeVpcAttribute",
        "ec2:DescribeAvailabilityZones"
      ],
      "Resource": "*"
    },
    {
      "Sid": "Subnets",
      "Effect": "Allow",
      "Action": [
        "ec2:CreateSubnet",
        "ec2:DeleteSubnet",
        "ec2:ModifySubnetAttribute",
        "ec2:DescribeSubnets"
      ],
      "Resource": "*"
    },
    {
      "Sid": "InternetGateway",
      "Effect": "Allow",
      "Action": [
        "ec2:CreateInternetGateway",
        "ec2:DeleteInternetGateway",
        "ec2:AttachInternetGateway",
        "ec2:DetachInternetGateway",
        "ec2:DescribeInternetGateways"
      ],
      "Resource": "*"
    },
    {
      "Sid": "RouteTables",
      "Effect": "Allow",
      "Action": [
        "ec2:CreateRouteTable",
        "ec2:DeleteRouteTable",
        "ec2:AssociateRouteTable",
        "ec2:DisassociateRouteTable",
        "ec2:CreateRoute",
        "ec2:DeleteRoute",
        "ec2:DescribeRouteTables"
      ],
      "Resource": "*"
    },
    {
      "Sid": "SecurityGroups",
      "Effect": "Allow",
      "Action": [
        "ec2:CreateSecurityGroup",
        "ec2:DeleteSecurityGroup",
        "ec2:DescribeSecurityGroups",
        "ec2:DescribeSecurityGroupRules",
        "ec2:AuthorizeSecurityGroupIngress",
        "ec2:AuthorizeSecurityGroupEgress",
        "ec2:RevokeSecurityGroupIngress",
        "ec2:RevokeSecurityGroupEgress",
        "ec2:UpdateSecurityGroupRuleDescriptionsIngress",
        "ec2:UpdateSecurityGroupRuleDescriptionsEgress"
      ],
      "Resource": "*"
    },
    {
      "Sid": "VpcEndpoints",
      "Effect": "Allow",
      "Action": [
        "ec2:CreateVpcEndpoint",
        "ec2:DeleteVpcEndpoints",
        "ec2:ModifyVpcEndpoint",
        "ec2:DescribeVpcEndpoints",
        "ec2:DescribePrefixLists"
      ],
      "Resource": "*"
    },
    {
      "Sid": "Tags",
      "Effect": "Allow",
      "Action": [
        "ec2:CreateTags",
        "ec2:DeleteTags",
        "ec2:DescribeTags"
      ],
      "Resource": "*"
    },
    {
      "Sid": "ECR",
      "Effect": "Allow",
      "Action": [
        "ecr:CreateRepository",
        "ecr:DeleteRepository",
        "ecr:DescribeRepositories",
        "ecr:PutLifecyclePolicy",
        "ecr:DeleteLifecyclePolicy",
        "ecr:PutImageScanningConfiguration",
        "ecr:PutImageTagMutability",
        "ecr:SetRepositoryPolicy",
        "ecr:DeleteRepositoryPolicy",
        "ecr:TagResource",
        "ecr:UntagResource",
        "ecr:ListTagsForResource"
      ],
      "Resource": "*"
    },
    {
      "Sid": "S3BucketManagement",
      "Effect": "Allow",
      "Action": [
        "s3:CreateBucket",
        "s3:DeleteBucket",
        "s3:GetBucketLocation",
        "s3:GetBucketPolicy",
        "s3:PutBucketPolicy",
        "s3:DeleteBucketPolicy",
        "s3:GetBucketPublicAccessBlock",
        "s3:PutBucketPublicAccessBlock",
        "s3:GetEncryptionConfiguration",
        "s3:PutEncryptionConfiguration",
        "s3:GetBucketTagging",
        "s3:PutBucketTagging",
        "s3:GetBucketVersioning",
        "s3:PutBucketVersioning",
        "s3:GetLifecycleConfiguration",
        "s3:PutLifecycleConfiguration"
      ],
      "Resource": "*"
    },
    {
      "Sid": "CloudFront",
      "Effect": "Allow",
      "Action": [
        "cloudfront:CreateDistribution",
        "cloudfront:UpdateDistribution",
        "cloudfront:DeleteDistribution",
        "cloudfront:GetDistribution",
        "cloudfront:GetDistributionConfig",
        "cloudfront:CreateOriginAccessControl",
        "cloudfront:UpdateOriginAccessControl",
        "cloudfront:DeleteOriginAccessControl",
        "cloudfront:GetOriginAccessControl",
        "cloudfront:GetOriginAccessControlConfig",
        "cloudfront:TagResource",
        "cloudfront:UntagResource",
        "cloudfront:ListTagsForResource"
      ],
      "Resource": "*"
    },
    {
      "Sid": "RDS",
      "Effect": "Allow",
      "Action": [
        "rds:CreateDBInstance",
        "rds:DeleteDBInstance",
        "rds:ModifyDBInstance",
        "rds:DescribeDBInstances",
        "rds:CreateDBSubnetGroup",
        "rds:DeleteDBSubnetGroup",
        "rds:ModifyDBSubnetGroup",
        "rds:DescribeDBSubnetGroups",
        "rds:AddTagsToResource",
        "rds:RemoveTagsFromResource",
        "rds:ListTagsForResource"
      ],
      "Resource": "*"
    },
    {
      "Sid": "SecretsManager",
      "Effect": "Allow",
      "Action": [
        "secretsmanager:CreateSecret",
        "secretsmanager:DeleteSecret",
        "secretsmanager:UpdateSecret",
        "secretsmanager:PutSecretValue",
        "secretsmanager:DescribeSecret",
        "secretsmanager:GetSecretValue",
        "secretsmanager:TagResource",
        "secretsmanager:UntagResource"
      ],
      "Resource": "*"
    },
    {
      "Sid": "IAMRoles",
      "Effect": "Allow",
      "Action": [
        "iam:CreateRole",
        "iam:DeleteRole",
        "iam:GetRole",
        "iam:UpdateRole",
        "iam:AttachRolePolicy",
        "iam:DetachRolePolicy",
        "iam:PutRolePolicy",
        "iam:DeleteRolePolicy",
        "iam:GetRolePolicy",
        "iam:TagRole",
        "iam:UntagRole",
        "iam:PassRole",
        "iam:CreateOpenIDConnectProvider",
        "iam:DeleteOpenIDConnectProvider",
        "iam:GetOpenIDConnectProvider",
        "iam:UpdateOpenIDConnectProviderThumbprint",
        "iam:AddClientIDToOpenIDConnectProvider",
        "iam:RemoveClientIDFromOpenIDConnectProvider",
        "iam:TagOpenIDConnectProvider"
      ],
      "Resource": "*"
    },
    {
      "Sid": "ECS",
      "Effect": "Allow",
      "Action": [
        "ecs:CreateCluster",
        "ecs:DeleteCluster",
        "ecs:DescribeClusters",
        "ecs:UpdateClusterSettings",
        "ecs:RegisterTaskDefinition",
        "ecs:DeregisterTaskDefinition",
        "ecs:DescribeTaskDefinition",
        "ecs:CreateService",
        "ecs:DeleteService",
        "ecs:UpdateService",
        "ecs:DescribeServices",
        "ecs:TagResource",
        "ecs:UntagResource",
        "ecs:ListTagsForResource"
      ],
      "Resource": "*"
    },
    {
      "Sid": "ELB",
      "Effect": "Allow",
      "Action": [
        "elasticloadbalancing:CreateLoadBalancer",
        "elasticloadbalancing:DeleteLoadBalancer",
        "elasticloadbalancing:DescribeLoadBalancers",
        "elasticloadbalancing:ModifyLoadBalancerAttributes",
        "elasticloadbalancing:CreateTargetGroup",
        "elasticloadbalancing:DeleteTargetGroup",
        "elasticloadbalancing:DescribeTargetGroups",
        "elasticloadbalancing:ModifyTargetGroup",
        "elasticloadbalancing:ModifyTargetGroupAttributes",
        "elasticloadbalancing:CreateListener",
        "elasticloadbalancing:DeleteListener",
        "elasticloadbalancing:DescribeListeners",
        "elasticloadbalancing:ModifyListener",
        "elasticloadbalancing:AddTags",
        "elasticloadbalancing:RemoveTags",
        "elasticloadbalancing:DescribeTags"
      ],
      "Resource": "*"
    },
    {
      "Sid": "CloudWatchLogs",
      "Effect": "Allow",
      "Action": [
        "logs:CreateLogGroup",
        "logs:DeleteLogGroup",
        "logs:DescribeLogGroups",
        "logs:PutRetentionPolicy",
        "logs:DeleteRetentionPolicy",
        "logs:TagLogGroup",
        "logs:TagResource",
        "logs:UntagResource"
      ],
      "Resource": "*"
    },
    {
      "Sid": "CloudWatchAlarms",
      "Effect": "Allow",
      "Action": [
        "cloudwatch:PutMetricAlarm",
        "cloudwatch:DeleteAlarms",
        "cloudwatch:DescribeAlarms",
        "cloudwatch:TagResource",
        "cloudwatch:UntagResource"
      ],
      "Resource": "*"
    },
    {
      "Sid": "ApplicationAutoScaling",
      "Effect": "Allow",
      "Action": [
        "application-autoscaling:RegisterScalableTarget",
        "application-autoscaling:DeregisterScalableTarget",
        "application-autoscaling:DescribeScalableTargets",
        "application-autoscaling:PutScalingPolicy",
        "application-autoscaling:DeleteScalingPolicy",
        "application-autoscaling:DescribeScalingPolicies"
      ],
      "Resource": "*"
    },
    {
      "Sid": "CodeDeploy",
      "Effect": "Allow",
      "Action": [
        "codedeploy:CreateApplication",
        "codedeploy:DeleteApplication",
        "codedeploy:GetApplication",
        "codedeploy:CreateDeploymentGroup",
        "codedeploy:DeleteDeploymentGroup",
        "codedeploy:UpdateDeploymentGroup",
        "codedeploy:GetDeploymentGroup",
        "codedeploy:TagResource",
        "codedeploy:UntagResource"
      ],
      "Resource": "*"
    },
    {
      "Sid": "CodePipeline",
      "Effect": "Allow",
      "Action": [
        "codepipeline:CreatePipeline",
        "codepipeline:DeletePipeline",
        "codepipeline:UpdatePipeline",
        "codepipeline:GetPipeline",
        "codepipeline:TagResource",
        "codepipeline:UntagResource"
      ],
      "Resource": "*"
    },
    {
      "Sid": "EventBridge",
      "Effect": "Allow",
      "Action": [
        "events:PutRule",
        "events:DeleteRule",
        "events:DescribeRule",
        "events:PutTargets",
        "events:RemoveTargets",
        "events:TagResource",
        "events:UntagResource",
        "events:ListTagsForResource"
      ],
      "Resource": "*"
    },
    {
      "Sid": "NestedStackTemplates",
      "Effect": "Allow",
      "Action": [
        "s3:GetObject",
        "s3:GetBucketLocation"
      ],
      "Resource": [
        "arn:aws:s3:::bem14-photo-uploader-stacks",
        "arn:aws:s3:::bem14-photo-uploader-stacks/*"
      ]
    },
    {
      "Sid": "NestedStacks",
      "Effect": "Allow",
      "Action": [
        "cloudformation:CreateStack",
        "cloudformation:UpdateStack",
        "cloudformation:DeleteStack",
        "cloudformation:DescribeStacks",
        "cloudformation:DescribeStackEvents",
        "cloudformation:GetTemplate",
        "cloudformation:ValidateTemplate",
        "cloudformation:CreateChangeSet",
        "cloudformation:DeleteChangeSet",
        "cloudformation:DescribeChangeSet",
        "cloudformation:ExecuteChangeSet"
      ],
      "Resource": "*"
    }
  ]
}
